 { "Teams": {
    "OKC": [ 
    {
    "Name":"Kevin Durant",
    "MP":"40:38",
    "FG":8,
    "FGA":22,
    "FG%":0.364,
    "3P":3,
    "3PA":9,
    "3P%":0.333,
    "FT":2,
    "FTA":4,
    "FT%":0.5,
    "ORB":0,
    "DRB":3,
    "TRB":3,
    "AST":3,
    "STL":1,
    "BLK":1,
    "TOV":2,
    "PF":0,
    "PTS":21,
    "+/-":-14
  },
  {
    "Name":"Russell Westbrook",
    "MP":"36:00",
    "FG":8,
    "FGA":16,
    "FG%":0.5,
    "3P":2,
    "3PA":4,
    "3P%":0.5,
    "FT":4,
    "FTA":6,
    "FT%":0.667,
    "ORB":1,
    "DRB":2,
    "TRB":3,
    "AST":11,
    "STL":3,
    "BLK":0,
    "TOV":4,
    "PF":3,
    "PTS":22,
    "+/-":-6
  },
  {
    "Name":"Serge Ibaka",
    "MP":"35:42",
    "FG":6,
    "FGA":16,
    "FG%":0.375,
    "3P":1,
    "3PA":3,
    "3P%":0.333,
    "FT":0,
    "FTA":0,
    "FT%":null,
    "ORB":2,
    "DRB":8,
    "TRB":10,
    "AST":1,
    "STL":1,
    "BLK":2,
    "TOV":2,
    "PF":2,
    "PTS":13,
    "+/-":-4
  },
  {
    "Name":"Steven Adams",
    "MP":"27:50",
    "FG":4,
    "FGA":6,
    "FG%":0.667,
    "3P":0,
    "3PA":0,
    "3P%":null,
    "FT":1,
    "FTA":2,
    "FT%":0.5,
    "ORB":3,
    "DRB":4,
    "TRB":7,
    "AST":1,
    "STL":0,
    "BLK":1,
    "TOV":1,
    "PF":4,
    "PTS":9,
    "+/-":-1
  },
  {
    "Name":"Andre Roberson",
    "MP":"15:21",
    "FG":2,
    "FGA":2,
    "FG%":1,
    "3P":2,
    "3PA":2,
    "3P%":1,
    "FT":0,
    "FTA":0,
    "FT%":null,
    "ORB":0,
    "DRB":1,
    "TRB":1,
    "AST":2,
    "STL":1,
    "BLK":0,
    "TOV":0,
    "PF":2,
    "PTS":6,
    "+/-":-1
  },
  {
    "Name":"Dion Waiters",
    "MP":"25:49",
    "FG":3,
    "FGA":8,
    "FG%":0.375,
    "3P":0,
    "3PA":1,
    "3P%":0,
    "FT":2,
    "FTA":2,
    "FT%":1,
    "ORB":0,
    "DRB":1,
    "TRB":1,
    "AST":1,
    "STL":3,
    "BLK":1,
    "TOV":1,
    "PF":1,
    "PTS":8,
    "+/-":-17
  },
  {
    "Name":"Reggie Jackson",
    "MP":"24:32",
    "FG":3,
    "FGA":8,
    "FG%":0.375,
    "3P":1,
    "3PA":3,
    "3P%":0.333,
    "FT":0,
    "FTA":0,
    "FT%":null,
    "ORB":1,
    "DRB":3,
    "TRB":4,
    "AST":3,
    "STL":2,
    "BLK":0,
    "TOV":0,
    "PF":2,
    "PTS":7,
    "+/-":-5
  },
  {
    "Name":"Anthony Morrow",
    "MP":"16:42",
    "FG":0,
    "FGA":4,
    "FG%":0,
    "3P":0,
    "3PA":2,
    "3P%":0,
    "FT":0,
    "FTA":0,
    "FT%":null,
    "ORB":1,
    "DRB":0,
    "TRB":1,
    "AST":0,
    "STL":0,
    "BLK":0,
    "TOV":1,
    "PF":1,
    "PTS":0,
    "+/-":-1
  },
  {
    "Name":"Kendrick Perkins",
    "MP":"15:02",
    "FG":1,
    "FGA":3,
    "FG%":0.333,
    "3P":0,
    "3PA":0,
    "3P%":null,
    "FT":2,
    "FTA":4,
    "FT%":0.5,
    "ORB":1,
    "DRB":5,
    "TRB":6,
    "AST":1,
    "STL":0,
    "BLK":2,
    "TOV":0,
    "PF":1,
    "PTS":4,
    "+/-":-10
  },
  {
    "Name":"Jeremy Lamb",
    "MP":"0:48",
    "FG":1,
    "FGA":1,
    "FG%":1,
    "3P":1,
    "3PA":1,
    "3P%":1,
    "FT":0,
    "FTA":0,
    "FT%":null,
    "ORB":0,
    "DRB":0,
    "TRB":0,
    "AST":0,
    "STL":0,
    "BLK":0,
    "TOV":0,
    "PF":0,
    "PTS":3,
    "+/-":3
  },
  {
    "Name":"Perry Jones",
    "MP":"0:48",
    "FG":0,
    "FGA":1,
    "FG%":0,
    "3P":0,
    "3PA":1,
    "3P%":0,
    "FT":0,
    "FTA":0,
    "FT%":null,
    "ORB":0,
    "DRB":0,
    "TRB":0,
    "AST":0,
    "STL":0,
    "BLK":0,
    "TOV":0,
    "PF":0,
    "PTS":0,
    "+/-":3
  },
  {
    "Name":"Ish Smith",
    "MP":"0:48",
    "FG":0,
    "FGA":0,
    "FG%":null,
    "3P":0,
    "3PA":0,
    "3P%":null,
    "FT":0,
    "FTA":0,
    "FT%":null,
    "ORB":0,
    "DRB":0,
    "TRB":0,
    "AST":0,
    "STL":0,
    "BLK":0,
    "TOV":0,
    "PF":0,
    "PTS":0,
    "+/-":3
  },
  {
    "Name":"OKC Team Totals",
    "MP":"240",
    "FG":36,
    "FGA":87,
    "FG%":0.414,
    "3P":10,
    "3PA":26,
    "3P%":0.385,
    "FT":11,
    "FTA":18,
    "FT%":0.611,
    "ORB":9,
    "DRB":27,
    "TRB":36,
    "AST":23,
    "STL":11,
    "BLK":7,
    "TOV":11,
    "PF":16,
    "PTS":93,
    "+/-":null
  }],

"ATL" : [
{
    "Name":"Paul Millsap",
    "MP":"33:10",
    "FG":9,
    "FGA":17,
    "FG%":0.529,
    "3P":2,
    "3PA":3,
    "3P%":0.667,
    "FT":2,
    "FTA":2,
    "FT%":1,
    "ORB":2,
    "DRB":8,
    "TRB":10,
    "AST":3,
    "STL":2,
    "BLK":2,
    "TOV":4,
    "PF":0,
    "PTS":22,
    "+/-":8
  },
  {
    "Name":"Kyle Korver",
    "MP":"32:50",
    "FG":2,
    "FGA":5,
    "FG%":0.4,
    "3P":1,
    "3PA":3,
    "3P%":0.333,
    "FT":0,
    "FTA":0,
    "FT%":null,
    "ORB":1,
    "DRB":3,
    "TRB":4,
    "AST":2,
    "STL":0,
    "BLK":0,
    "TOV":4,
    "PF":1,
    "PTS":5,
    "+/-":10
  },
  {
    "Name":"Al Horford",
    "MP":"32:00",
    "FG":6,
    "FGA":12,
    "FG%":0.5,
    "3P":1,
    "3PA":2,
    "3P%":0.5,
    "FT":1,
    "FTA":1,
    "FT%":1,
    "ORB":3,
    "DRB":9,
    "TRB":12,
    "AST":3,
    "STL":1,
    "BLK":3,
    "TOV":1,
    "PF":1,
    "PTS":14,
    "+/-":11
  },
  {
    "Name":"DeMarre Carroll",
    "MP":"31:46",
    "FG":5,
    "FGA":7,
    "FG%":0.714,
    "3P":3,
    "3PA":5,
    "3P%":0.6,
    "FT":0,
    "FTA":0,
    "FT%":null,
    "ORB":1,
    "DRB":3,
    "TRB":4,
    "AST":3,
    "STL":0,
    "BLK":0,
    "TOV":0,
    "PF":3,
    "PTS":13,
    "+/-":3
  },
  {
    "Name":"Jeff Teague",
    "MP":"30:07",
    "FG":7,
    "FGA":13,
    "FG%":0.538,
    "3P":1,
    "3PA":2,
    "3P%":0.5,
    "FT":2,
    "FTA":2,
    "FT%":1,
    "ORB":0,
    "DRB":2,
    "TRB":2,
    "AST":9,
    "STL":1,
    "BLK":0,
    "TOV":2,
    "PF":2,
    "PTS":17,
    "+/-":6
  },
  {
    "Name":"Pero Antic",
    "MP":"18:38",
    "FG":2,
    "FGA":6,
    "FG%":0.333,
    "3P":1,
    "3PA":4,
    "3P%":0.25,
    "FT":3,
    "FTA":3,
    "FT%":1,
    "ORB":1,
    "DRB":3,
    "TRB":4,
    "AST":2,
    "STL":0,
    "BLK":0,
    "TOV":0,
    "PF":3,
    "PTS":8,
    "+/-":2
  },
  {
    "Name":"Dennis Schroder",
    "MP":"17:53",
    "FG":4,
    "FGA":11,
    "FG%":0.364,
    "3P":1,
    "3PA":5,
    "3P%":0.2,
    "FT":4,
    "FTA":4,
    "FT%":1,
    "ORB":0,
    "DRB":4,
    "TRB":4,
    "AST":5,
    "STL":0,
    "BLK":0,
    "TOV":1,
    "PF":1,
    "PTS":13,
    "+/-":4
  },
  {
    "Name":"Kent Bazemore",
    "MP":"16:13",
    "FG":2,
    "FGA":5,
    "FG%":0.4,
    "3P":0,
    "3PA":1,
    "3P%":0,
    "FT":1,
    "FTA":1,
    "FT%":1,
    "ORB":1,
    "DRB":1,
    "TRB":2,
    "AST":0,
    "STL":1,
    "BLK":0,
    "TOV":1,
    "PF":1,
    "PTS":5,
    "+/-":3
  },
  {
    "Name":"Thabo Sefolosha",
    "MP":"15:52",
    "FG":2,
    "FGA":2,
    "FG%":1,
    "3P":0,
    "3PA":0,
    "3P%":null,
    "FT":0,
    "FTA":0,
    "FT%":null,
    "ORB":0,
    "DRB":4,
    "TRB":4,
    "AST":0,
    "STL":0,
    "BLK":0,
    "TOV":2,
    "PF":1,
    "PTS":4,
    "+/-":0
  },
  {
    "Name":"Mike Scott",
    "MP":"11:31",
    "FG":1,
    "FGA":5,
    "FG%":0.2,
    "3P":0,
    "3PA":0,
    "3P%":null,
    "FT":0,
    "FTA":0,
    "FT%":null,
    "ORB":1,
    "DRB":0,
    "TRB":1,
    "AST":0,
    "STL":1,
    "BLK":0,
    "TOV":1,
    "PF":0,
    "PTS":2,
    "+/-":3
  },
  {
    "Name":"ATL Team Totals",
    "MP":"240",
    "FG":40,
    "FGA":83,
    "FG%":0.482,
    "3P":10,
    "3PA":25,
    "3P%":0.4,
    "FT":13,
    "FTA":13,
    "FT%":1,
    "ORB":10,
    "DRB":37,
    "TRB":47,
    "AST":27,
    "STL":6,
    "BLK":5,
    "TOV":16,
    "PF":13,
    "PTS":103,
    "+/-":null
  }
  ]
}
}